{"id":{"showToUser":"false","propertyName":"id","dbName":"IdCisloBal","name":"ID","title":"ID","type":"integer","isVisible":"true","isSortable":"true","isHighlight":"false","inId":"true","inSummary":"true","inDetail":"true","mandatory":"false","isWritable":"false","isOverWritable":"false","hasBusinessLogic":"false","isUpperCase":"false","isLowerCase":"false","links":null},"lastUpdate":{"showToUser":"false","propertyName":"lastUpdate","dbName":"lastUpdate","name":"Posledn\u00ed zm\u011bna","title":"Posledn\u00ed zm\u011bna","type":"datetime","isVisible":"true","isSortable":"false","isHighlight":"false","inId":"false","inSummary":"true","inDetail":"true","mandatory":"false","isWritable":"false","isOverWritable":"false","hasBusinessLogic":"true","isUpperCase":"false","isLowerCase":"false","links":null},"cislo":{"showToUser":"true","propertyName":"cislo","dbName":"Cislo","name":"\u010c\u00edslo","title":"\u010c\u00edslo","type":"string","isVisible":"true","isSortable":"true","isHighlight":"false","inId":"false","inSummary":"false","inDetail":"true","mandatory":"false","maxLength":"100","isWritable":"true","isOverWritable":"true","hasBusinessLogic":"false","isUpperCase":"false","isLowerCase":"false","links":null},"formaDopravy":{"showToUser":"true","propertyName":"formaDopravy","dbName":"IdFormaDopravy","name":"Forma dopravy","title":"Forma dopravy","type":"relation","fkName":"Formy dopravy 20038","fkEvidencePath":"forma-dopravy","fkEvidenceType":"FORMA_DOPRAVY","isVisible":"true","isSortable":"true","isHighlight":"false","inId":"false","inSummary":"false","inDetail":"true","mandatory":"false","isWritable":"true","isOverWritable":"true","hasBusinessLogic":"false","isUpperCase":"false","isLowerCase":"false","url":"http:\/\/vitexsoftware.flexibee.eu:5434\/c\/flexipeehp\/forma-dopravy","links":null},"doklFak":{"showToUser":"true","propertyName":"doklFak","dbName":"IdDoklFak","name":"Doklad faktury","title":"Doklad faktury","type":"relation","isVisible":"true","isSortable":"true","isHighlight":"false","inId":"false","inSummary":"false","inDetail":"true","mandatory":"false","isWritable":"true","isOverWritable":"true","hasBusinessLogic":"false","isUpperCase":"false","isLowerCase":"false","evidenceVariants":{"evidenceVariant":["zavazek","pohledavka","prodejka","faktura-vydana","faktura-prijata"]},"links":null},"doklSklad":{"showToUser":"true","propertyName":"doklSklad","dbName":"IdDoklSklad","name":"P\u0159\u00edjemka\/v\u00fddejka","title":"P\u0159\u00edjemka\/v\u00fddejka","type":"relation","isVisible":"true","isSortable":"true","isHighlight":"false","inId":"false","inSummary":"false","inDetail":"true","mandatory":"false","isWritable":"true","isOverWritable":"true","hasBusinessLogic":"false","isUpperCase":"false","isLowerCase":"false","evidenceVariants":{"evidenceVariant":"skladovy-pohyb"},"links":null},"doklObch":{"showToUser":"true","propertyName":"doklObch","dbName":"IdDoklObch","name":"Obchodn\u00ed doklad","title":"Obchodn\u00ed doklad","type":"relation","isVisible":"true","isSortable":"true","isHighlight":"false","inId":"false","inSummary":"false","inDetail":"true","mandatory":"false","isWritable":"true","isOverWritable":"true","hasBusinessLogic":"false","isUpperCase":"false","isLowerCase":"false","evidenceVariants":{"evidenceVariant":["poptavka-vydana","objednavka-vydana","poptavka-prijata","nabidka-vydana","objednavka-prijata","nabidka-prijata"]},"links":null}}