{"id":{"showToUser":"false","propertyName":"id","dbName":"IdUcet","name":"ID","title":"ID","type":"integer","isVisible":"true","isSortable":"true","isHighlight":"false","inId":"true","inSummary":"true","inDetail":"true","mandatory":"false","isWritable":"false","isOverWritable":"false","hasBusinessLogic":"false","isUpperCase":"false","isLowerCase":"false","links":null},"lastUpdate":{"showToUser":"false","propertyName":"lastUpdate","dbName":"lastUpdate","name":"Posledn\u00ed zm\u011bna","title":"Posledn\u00ed zm\u011bna","type":"datetime","isVisible":"true","isSortable":"false","isHighlight":"false","inId":"false","inSummary":"true","inDetail":"true","mandatory":"false","isWritable":"false","isOverWritable":"false","hasBusinessLogic":"true","isUpperCase":"false","isLowerCase":"false","links":null},"kod":{"showToUser":"true","propertyName":"kod","dbName":"Kod","name":"\u00da\u010det","title":"\u010c\u00edslo \u00fa\u010dtu","type":"string","isVisible":"true","isSortable":"true","isHighlight":"false","inId":"false","inSummary":"true","inDetail":"true","mandatory":"true","minLength":"3","maxLength":"6","isWritable":"true","isOverWritable":"true","hasBusinessLogic":"true","isUpperCase":"false","isLowerCase":"false","links":null},"nazev":{"showToUser":"true","propertyName":"nazev","dbName":"Nazev","name":"N\u00e1zev","title":"N\u00e1zev","type":"string","isVisible":"true","isSortable":"true","isHighlight":"false","inId":"false","inSummary":"true","inDetail":"true","mandatory":"true","maxLength":"255","isWritable":"true","isOverWritable":"true","hasBusinessLogic":"false","isUpperCase":"false","isLowerCase":"false","links":null},"nazevA":{"showToUser":"true","propertyName":"nazevA","dbName":"NazevA","name":"N\u00e1zev EN","title":"N\u00e1zev EN","type":"string","isVisible":"true","isSortable":"true","isHighlight":"false","inId":"false","inSummary":"false","inDetail":"true","mandatory":"false","maxLength":"255","isWritable":"true","isOverWritable":"true","hasBusinessLogic":"false","isUpperCase":"false","isLowerCase":"false","links":null},"nazevB":{"showToUser":"true","propertyName":"nazevB","dbName":"NazevB","name":"N\u00e1zev DE","title":"N\u00e1zev DE","type":"string","isVisible":"true","isSortable":"true","isHighlight":"false","inId":"false","inSummary":"false","inDetail":"true","mandatory":"false","maxLength":"255","isWritable":"true","isOverWritable":"true","hasBusinessLogic":"false","isUpperCase":"false","isLowerCase":"false","links":null},"nazevC":{"showToUser":"true","propertyName":"nazevC","dbName":"NazevC","name":"N\u00e1zev FR","title":"N\u00e1zev FR","type":"string","isVisible":"true","isSortable":"true","isHighlight":"false","inId":"false","inSummary":"false","inDetail":"true","mandatory":"false","maxLength":"255","isWritable":"true","isOverWritable":"true","hasBusinessLogic":"false","isUpperCase":"false","isLowerCase":"false","links":null},"poznam":{"showToUser":"true","propertyName":"poznam","dbName":"Poznam","name":"Pozn\u00e1mka","title":"Pozn\u00e1mka","type":"string","isVisible":"true","isSortable":"true","isHighlight":"false","inId":"false","inSummary":"false","inDetail":"true","mandatory":"false","isWritable":"true","isOverWritable":"true","hasBusinessLogic":"false","isUpperCase":"false","isLowerCase":"false","links":null},"popis":{"showToUser":"true","propertyName":"popis","dbName":"Popis","name":"Popis","title":"Popis","type":"string","isVisible":"true","isSortable":"true","isHighlight":"false","inId":"false","inSummary":"false","inDetail":"true","mandatory":"false","isWritable":"true","isOverWritable":"true","hasBusinessLogic":"false","isUpperCase":"false","isLowerCase":"false","links":null},"ucetObdobiOd":{"showToUser":"true","propertyName":"ucetObdobiOd","dbName":"IdUcetObdobiOd","name":"Plat\u00ed od","title":"Plat\u00ed od","type":"relation","fkName":"\u00da\u010detn\u00ed obdob\u00ed 1005","fkEvidencePath":"ucetni-obdobi","fkEvidenceType":"UCETNI_OBDOBI","isVisible":"true","isSortable":"true","isHighlight":"false","inId":"false","inSummary":"false","inDetail":"true","mandatory":"false","isWritable":"true","isOverWritable":"true","hasBusinessLogic":"true","isUpperCase":"false","isLowerCase":"false","url":"http:\/\/vitexsoftware.flexibee.eu:5434\/c\/flexipeehp\/ucetni-obdobi","links":null},"ucetObdobiDo":{"showToUser":"true","propertyName":"ucetObdobiDo","dbName":"IdUcetObdobiDo","name":"Plat\u00ed do","title":"Plat\u00ed do","type":"relation","fkName":"\u00da\u010detn\u00ed obdob\u00ed 1005","fkEvidencePath":"ucetni-obdobi","fkEvidenceType":"UCETNI_OBDOBI","isVisible":"true","isSortable":"true","isHighlight":"false","inId":"false","inSummary":"false","inDetail":"true","mandatory":"false","isWritable":"true","isOverWritable":"true","hasBusinessLogic":"true","isUpperCase":"false","isLowerCase":"false","url":"http:\/\/vitexsoftware.flexibee.eu:5434\/c\/flexipeehp\/ucetni-obdobi","links":null},"danovy":{"showToUser":"true","propertyName":"danovy","dbName":"Danovy","name":"Da\u0148ov\u00fd","title":"Da\u0148ov\u00fd","type":"logic","isVisible":"true","isSortable":"true","isHighlight":"false","inId":"false","inSummary":"false","inDetail":"true","mandatory":"false","isWritable":"true","isOverWritable":"true","hasBusinessLogic":"false","isUpperCase":"false","isLowerCase":"false","links":null},"saldo":{"showToUser":"true","propertyName":"saldo","dbName":"Saldo","name":"Saldo","title":"Saldo","type":"logic","isVisible":"true","isSortable":"true","isHighlight":"false","inId":"false","inSummary":"false","inDetail":"true","mandatory":"false","isWritable":"true","isOverWritable":"true","hasBusinessLogic":"false","isUpperCase":"false","isLowerCase":"false","links":null},"typUctuK":{"showToUser":"true","propertyName":"typUctuK","dbName":"TypUctuK","name":"Typ \u00fa\u010dtu","title":"Typ \u00fa\u010dtu","type":"select","isVisible":"true","isSortable":"true","isHighlight":"false","inId":"false","inSummary":"false","inDetail":"true","mandatory":"false","maxLength":"50","isWritable":"true","isOverWritable":"true","hasBusinessLogic":"true","isUpperCase":"false","isLowerCase":"false","links":null,"values":{"value":[{"@key":"typUctu.rozvahovy","$":"rozvahov\u00fd"},{"@key":"typUctu.vysledkovy","$":"v\u00fdsledkov\u00fd"},{"@key":"typUctu.podrozvahovy","$":"podrozvahov\u00fd"},{"@key":"typUctu.zaverkovy","$":"z\u00e1v\u011brkov\u00fd"},{"@key":"typUctu.vnitropodnikovy","$":"vnitropodnikov\u00fd"}]}},"druhUctuK":{"showToUser":"true","propertyName":"druhUctuK","dbName":"DruhUctuK","name":"Druh \u00fa\u010dtu","title":"Druh \u00fa\u010dtu","type":"select","isVisible":"true","isSortable":"true","isHighlight":"false","inId":"false","inSummary":"false","inDetail":"true","mandatory":"false","maxLength":"50","isWritable":"false","isOverWritable":"false","hasBusinessLogic":"false","isUpperCase":"false","isLowerCase":"false","links":null,"values":{"value":[{"@key":"druhUctu.aktivni","$":"aktivn\u00ed"},{"@key":"druhUctu.aktpasvy","$":"aktivn\u00ed\/pasivn\u00ed (dle v\u00fdsledku)"},{"@key":"druhUctu.pasivni","$":"pasivn\u00ed"},{"@key":"druhUctu.pasivhvy","$":"pasivn\u00ed - h. v\u00fdsledek"},{"@key":"druhUctu.naklady","$":"n\u00e1klady"},{"@key":"druhUctu.vynosy","$":"v\u00fdnosy"},{"@key":"druhUctu.otevknih","$":"otev\u0159en\u00ed knihy"},{"@key":"druhUctu.uzavknih","$":"uzav\u0159en\u00ed knihy"},{"@key":"druhUctu.prhosvys","$":"p\u0159evod hospod\u00e1\u0159sk\u00e9ho v\u00fdsledku"}]}},"mena":{"showToUser":"true","propertyName":"mena","dbName":"IdMeny","name":"M\u011bna","title":"M\u011bna","type":"relation","fkName":"M\u011bny 20005","fkEvidencePath":"mena","fkEvidenceType":"MENA","isVisible":"true","isSortable":"true","isHighlight":"false","inId":"false","inSummary":"true","inDetail":"true","mandatory":"false","isWritable":"true","isOverWritable":"true","hasBusinessLogic":"false","isUpperCase":"false","isLowerCase":"false","url":"http:\/\/vitexsoftware.flexibee.eu:5434\/c\/flexipeehp\/mena","links":null},"stdUcet":{"showToUser":"true","propertyName":"stdUcet","dbName":"IdStdUcet","name":"Syntetick\u00fd \u00fa\u010det","title":"Syntetick\u00fd \u00fa\u010det","type":"relation","fkName":"Standardn\u00ed \u00fa\u010detn\u00ed osnova 20023","fkEvidencePath":"ucetni-osnova","fkEvidenceType":"UCETNI_OSNOVA","isVisible":"true","isSortable":"true","isHighlight":"false","inId":"false","inSummary":"false","inDetail":"true","mandatory":"false","minLength":"3","maxLength":"3","isWritable":"false","isOverWritable":"false","hasBusinessLogic":"true","isUpperCase":"true","isLowerCase":"false","url":"http:\/\/vitexsoftware.flexibee.eu:5434\/c\/flexipeehp\/ucetni-osnova","links":null},"typOrganizace":{"showToUser":"true","propertyName":"typOrganizace","dbName":"IdTypOrg","name":"Typ organizace","title":"Typ organizace","type":"relation","fkName":"Typ organizace 3101","fkEvidencePath":"typ-organizace","fkEvidenceType":"TYP_ORGANIZACE","isVisible":"true","isSortable":"true","isHighlight":"false","inId":"false","inSummary":"false","inDetail":"true","mandatory":"false","maxLength":"20","isWritable":"false","isOverWritable":"false","hasBusinessLogic":"false","isUpperCase":"true","isLowerCase":"false","url":"http:\/\/vitexsoftware.flexibee.eu:5434\/c\/flexipeehp\/typ-organizace","links":null}}