{"kod":{"showToUser":"true","propertyName":"kod","name":"Doklad","title":"Doklad","type":"string","isVisible":"true","isSortable":"true","isHighlight":"false","inId":"false","inSummary":"true","inDetail":"true","mandatory":"false","isWritable":"true","isOverWritable":"true","hasBusinessLogic":"false","isUpperCase":"false","isLowerCase":"false","links":null},"verze":{"showToUser":"true","propertyName":"verze","name":"Verze kom. protokolu","title":"Verze kom. protokolu","type":"integer","isVisible":"true","isSortable":"true","isHighlight":"false","inId":"false","inSummary":"false","inDetail":"true","mandatory":"true","isWritable":"true","isOverWritable":"true","hasBusinessLogic":"false","isUpperCase":"false","isLowerCase":"false","links":null},"storno":{"showToUser":"true","propertyName":"storno","name":"Storno","title":"Storno","type":"logic","isVisible":"true","isSortable":"true","isHighlight":"false","inId":"false","inSummary":"true","inDetail":"true","mandatory":"false","isWritable":"true","isOverWritable":"true","hasBusinessLogic":"false","isUpperCase":"false","isLowerCase":"false","links":null},"odeslano":{"showToUser":"true","propertyName":"odeslano","name":"Odesl\u00e1no","title":"Odesl\u00e1no","type":"logic","isVisible":"true","isSortable":"true","isHighlight":"false","inId":"false","inSummary":"true","inDetail":"true","mandatory":"false","isWritable":"true","isOverWritable":"true","hasBusinessLogic":"false","isUpperCase":"false","isLowerCase":"false","links":null},"cas":{"showToUser":"true","propertyName":"cas","name":"\u010cas 1. odpov\u011bdi","title":"\u010cas 1. odpov\u011bdi","type":"string","isVisible":"true","isSortable":"true","isHighlight":"false","inId":"false","inSummary":"true","inDetail":"true","mandatory":"false","isWritable":"true","isOverWritable":"true","hasBusinessLogic":"false","isUpperCase":"false","isLowerCase":"false","links":null},"casPosl":{"showToUser":"true","propertyName":"casPosl","name":"\u010cas posledn\u00ed odpov\u011bdi","title":"\u010cas posledn\u00ed odpov\u011bdi","type":"string","isVisible":"true","isSortable":"true","isHighlight":"false","inId":"false","inSummary":"true","inDetail":"true","mandatory":"false","isWritable":"true","isOverWritable":"true","hasBusinessLogic":"false","isUpperCase":"false","isLowerCase":"false","links":null},"eetModK":{"showToUser":"true","propertyName":"eetModK","name":"M\u00f3d komunikace","title":"M\u00f3d komunikace","type":"select","isVisible":"true","isSortable":"true","isHighlight":"false","inId":"false","inSummary":"true","inDetail":"true","mandatory":"false","maxLength":"50","isWritable":"true","isOverWritable":"true","hasBusinessLogic":"false","isUpperCase":"false","isLowerCase":"false","links":null,"values":{"value":[{"@key":"eetMod.ostry","$":"Ostr\u00fd"},{"@key":"eetMod.overovaci","$":"Ov\u011b\u0159ovac\u00ed"},{"@key":"eetMod.ostryTest","$":"Neproduk\u010dn\u00ed ostr\u00fd (pro v\u00fdvoj\u00e1\u0159e)"},{"@key":"eetMod.overovaciTest","$":"Neproduk\u010dn\u00ed ov\u011b\u0159ovac\u00ed (pro v\u00fdvoj\u00e1\u0159e)"},{"@key":"eetMod.ne","$":"Vypnuto"}]}},"eetTypK":{"showToUser":"true","propertyName":"eetTypK","name":"Re\u017eim EET","title":"Re\u017eim EET","type":"select","isVisible":"true","isSortable":"true","isHighlight":"false","inId":"false","inSummary":"true","inDetail":"true","mandatory":"false","maxLength":"50","isWritable":"true","isOverWritable":"true","hasBusinessLogic":"false","isUpperCase":"false","isLowerCase":"false","links":null,"values":{"value":[{"@key":"eetTyp.ne","$":"nepodl\u00e9h\u00e1 EET"},{"@key":"eetTyp.anoBezny","$":"b\u011b\u017en\u00fd re\u017eim"},{"@key":"eetTyp.anoZjednoduseny","$":"zjednodu\u0161en\u00fd re\u017eim"}]}},"doklEetTypK":{"showToUser":"true","propertyName":"doklEetTypK","name":"Re\u017eim EET (doklad)","title":"Re\u017eim EET (doklad)","type":"select","isVisible":"true","isSortable":"true","isHighlight":"false","inId":"false","inSummary":"false","inDetail":"true","mandatory":"false","maxLength":"50","isWritable":"true","isOverWritable":"true","hasBusinessLogic":"false","isUpperCase":"false","isLowerCase":"false","links":null,"values":{"value":[{"@key":"eetTyp.ne","$":"nepodl\u00e9h\u00e1 EET"},{"@key":"eetTyp.anoBezny","$":"b\u011b\u017en\u00fd re\u017eim"},{"@key":"eetTyp.anoZjednoduseny","$":"zjednodu\u0161en\u00fd re\u017eim"}]}},"chyba":{"showToUser":"true","propertyName":"chyba","name":"Informace o chyb\u011b","title":"Informace o chyb\u011b","type":"string","isVisible":"true","isSortable":"true","isHighlight":"false","inId":"false","inSummary":"true","inDetail":"true","mandatory":"false","maxLength":"255","isWritable":"true","isOverWritable":"true","hasBusinessLogic":"false","isUpperCase":"false","isLowerCase":"false","links":null},"varovani":{"showToUser":"true","propertyName":"varovani","name":"Varov\u00e1n\u00ed","title":"Varov\u00e1n\u00ed","type":"string","isVisible":"true","isSortable":"true","isHighlight":"false","inId":"false","inSummary":"true","inDetail":"true","mandatory":"false","maxLength":"255","isWritable":"true","isOverWritable":"true","hasBusinessLogic":"false","isUpperCase":"false","isLowerCase":"false","links":null},"zprava":{"showToUser":"true","propertyName":"zprava","name":"1. zpr\u00e1va","title":"1. zpr\u00e1va","type":"string","isVisible":"true","isSortable":"true","isHighlight":"false","inId":"false","inSummary":"false","inDetail":"true","mandatory":"false","isWritable":"true","isOverWritable":"true","hasBusinessLogic":"false","isUpperCase":"false","isLowerCase":"false","links":null},"odpoved":{"showToUser":"true","propertyName":"odpoved","name":"1. odpov\u011b\u010f","title":"1. odpov\u011b\u010f","type":"string","isVisible":"true","isSortable":"true","isHighlight":"false","inId":"false","inSummary":"false","inDetail":"true","mandatory":"false","isWritable":"true","isOverWritable":"true","hasBusinessLogic":"false","isUpperCase":"false","isLowerCase":"false","links":null},"zpravaPosl":{"showToUser":"true","propertyName":"zpravaPosl","name":"Posledn\u00ed zpr\u00e1va","title":"Posledn\u00ed zpr\u00e1va","type":"string","isVisible":"true","isSortable":"true","isHighlight":"false","inId":"false","inSummary":"false","inDetail":"true","mandatory":"false","isWritable":"true","isOverWritable":"true","hasBusinessLogic":"false","isUpperCase":"false","isLowerCase":"false","links":null},"odpovedPosl":{"showToUser":"true","propertyName":"odpovedPosl","name":"Posledn\u00ed odpov\u011b\u010f","title":"Posledn\u00ed odpov\u011b\u010f","type":"string","isVisible":"true","isSortable":"true","isHighlight":"false","inId":"false","inSummary":"false","inDetail":"true","mandatory":"false","isWritable":"true","isOverWritable":"true","hasBusinessLogic":"false","isUpperCase":"false","isLowerCase":"false","links":null},"celkTrzba":{"showToUser":"true","propertyName":"celkTrzba","name":"Celkem tr\u017eba","title":"Celkem tr\u017eba","type":"numeric","isVisible":"true","isSortable":"true","isHighlight":"false","inId":"false","inSummary":"false","inDetail":"true","mandatory":"false","digits":"15","decimal":"2","isWritable":"true","isOverWritable":"true","hasBusinessLogic":"false","isUpperCase":"false","isLowerCase":"false","links":null},"sumOsv":{"showToUser":"true","propertyName":"sumOsv","name":"Osvob., bez DPH [K\u010d]","title":"0 %","type":"numeric","isVisible":"true","isSortable":"true","isHighlight":"false","inId":"false","inSummary":"false","inDetail":"true","mandatory":"false","digits":"15","decimal":"2","isWritable":"true","isOverWritable":"true","hasBusinessLogic":"false","isUpperCase":"false","isLowerCase":"false","links":null},"sumZklZakl":{"showToUser":"true","propertyName":"sumZklZakl","name":"Z\u00e1klad DPH z\u00e1kl. [K\u010d]","title":"Z\u00e1klad DPH z\u00e1kl. [K\u010d]","type":"numeric","isVisible":"true","isSortable":"true","isHighlight":"false","inId":"false","inSummary":"false","inDetail":"true","mandatory":"false","digits":"15","decimal":"2","isWritable":"true","isOverWritable":"true","hasBusinessLogic":"false","isUpperCase":"false","isLowerCase":"false","links":null},"sumDphZakl":{"showToUser":"true","propertyName":"sumDphZakl","name":"DPH z\u00e1kladn\u00ed [K\u010d]","title":"DPH z\u00e1kladn\u00ed","type":"numeric","isVisible":"true","isSortable":"true","isHighlight":"false","inId":"false","inSummary":"false","inDetail":"true","mandatory":"false","digits":"15","decimal":"2","isWritable":"true","isOverWritable":"true","hasBusinessLogic":"false","isUpperCase":"false","isLowerCase":"false","links":null},"sumZklSniz":{"showToUser":"true","propertyName":"sumZklSniz","name":"Z\u00e1klad DPH sn\u00ed\u017e. [K\u010d]","title":"Z\u00e1klad DPH sn\u00ed\u017e. [K\u010d]","type":"numeric","isVisible":"true","isSortable":"true","isHighlight":"false","inId":"false","inSummary":"false","inDetail":"true","mandatory":"false","digits":"15","decimal":"2","isWritable":"true","isOverWritable":"true","hasBusinessLogic":"false","isUpperCase":"false","isLowerCase":"false","links":null},"sumDphSniz":{"showToUser":"true","propertyName":"sumDphSniz","name":"DPH sn\u00ed\u017een\u00e1 [K\u010d]","title":"DPH sn\u00ed\u017een\u00e1","type":"numeric","isVisible":"true","isSortable":"true","isHighlight":"false","inId":"false","inSummary":"false","inDetail":"true","mandatory":"false","digits":"15","decimal":"2","isWritable":"true","isOverWritable":"true","hasBusinessLogic":"false","isUpperCase":"false","isLowerCase":"false","links":null},"sumZklSniz2":{"showToUser":"true","propertyName":"sumZklSniz2","name":"Z\u00e1klad DPH 2. sn\u00ed\u017e. [K\u010d]","title":"Z\u00e1klad DPH 2. sn\u00ed\u017e. [K\u010d]","type":"numeric","isVisible":"true","isSortable":"true","isHighlight":"false","inId":"false","inSummary":"false","inDetail":"true","mandatory":"false","digits":"15","decimal":"2","isWritable":"true","isOverWritable":"true","hasBusinessLogic":"false","isUpperCase":"false","isLowerCase":"false","links":null},"sumDphSniz2":{"showToUser":"true","propertyName":"sumDphSniz2","name":"DPH 2. sn\u00ed\u017een\u00e1 [K\u010d]","title":"DPH 2. sn\u00ed\u017een\u00e1","type":"numeric","isVisible":"true","isSortable":"true","isHighlight":"false","inId":"false","inSummary":"false","inDetail":"true","mandatory":"false","digits":"15","decimal":"2","isWritable":"true","isOverWritable":"true","hasBusinessLogic":"false","isUpperCase":"false","isLowerCase":"false","links":null},"cestSluz":{"showToUser":"true","propertyName":"cestSluz","name":"Celkem cestovn\u00ed","title":"Celkem cestovn\u00ed","type":"numeric","isVisible":"true","isSortable":"true","isHighlight":"false","inId":"false","inSummary":"false","inDetail":"true","mandatory":"false","digits":"15","decimal":"2","isWritable":"true","isOverWritable":"true","hasBusinessLogic":"false","isUpperCase":"false","isLowerCase":"false","links":null},"pouzitZboz1":{"showToUser":"true","propertyName":"pouzitZboz1","name":"Pou\u017eit\u00e9 zb. z\u00e1kl.","title":"Pou\u017eit\u00e9 zb. z\u00e1kl.","type":"numeric","isVisible":"true","isSortable":"true","isHighlight":"false","inId":"false","inSummary":"false","inDetail":"true","mandatory":"false","digits":"15","decimal":"2","isWritable":"true","isOverWritable":"true","hasBusinessLogic":"false","isUpperCase":"false","isLowerCase":"false","links":null},"pouzitZboz2":{"showToUser":"true","propertyName":"pouzitZboz2","name":"Pou\u017eit\u00e9 zb. sn\u00ed\u017e.","title":"Pou\u017eit\u00e9 zb. sn\u00ed\u017e.","type":"numeric","isVisible":"true","isSortable":"true","isHighlight":"false","inId":"false","inSummary":"false","inDetail":"true","mandatory":"false","digits":"15","decimal":"2","isWritable":"true","isOverWritable":"true","hasBusinessLogic":"false","isUpperCase":"false","isLowerCase":"false","links":null},"pouzitZboz3":{"showToUser":"true","propertyName":"pouzitZboz3","name":"Pou\u017eit\u00e9 zb. 2. sn\u00ed\u017e.","title":"Pou\u017eit\u00e9 zb. 2. sn\u00ed\u017e.","type":"numeric","isVisible":"true","isSortable":"true","isHighlight":"false","inId":"false","inSummary":"false","inDetail":"true","mandatory":"false","digits":"15","decimal":"2","isWritable":"true","isOverWritable":"true","hasBusinessLogic":"false","isUpperCase":"false","isLowerCase":"false","links":null},"urcenoCerpZuct":{"showToUser":"true","propertyName":"urcenoCerpZuct","name":"K \u010derp\u00e1n\u00ed","title":"K \u010derp\u00e1n\u00ed","type":"numeric","isVisible":"true","isSortable":"true","isHighlight":"false","inId":"false","inSummary":"false","inDetail":"true","mandatory":"false","digits":"15","decimal":"2","isWritable":"true","isOverWritable":"true","hasBusinessLogic":"false","isUpperCase":"false","isLowerCase":"false","links":null},"cerpZuct":{"showToUser":"true","propertyName":"cerpZuct","name":"\u010cerp\u00e1no","title":"\u010cerp\u00e1no","type":"numeric","isVisible":"true","isSortable":"true","isHighlight":"false","inId":"false","inSummary":"false","inDetail":"true","mandatory":"false","digits":"15","decimal":"2","isWritable":"true","isOverWritable":"true","hasBusinessLogic":"false","isUpperCase":"false","isLowerCase":"false","links":null}}